[
  {
    "action": "播撒初始和谐之光，引导混沌元素相互交融",
    "impact": 0.8,
    "agent": "同谐",
    "round": 1,
    "step": 1,
    "timestamp": "2025-07-14T07:10:07.645656",
    "reward": 0.6200000000000001
  },
  {
    "action": "记录初始和谐之光的播撒过程与混沌元素交融的细节",
    "impact": 0.7,
    "agent": "记忆",
    "round": 1,
    "step": 1,
    "timestamp": "2025-07-14T07:10:09.709028",
    "reward": 0.58
  },
  {
    "action": "```json\n{\n  \"action\": \"构筑初始秩序框架，规范混沌元素的交融路径\",\n  \"impact\": 0.9\n}\n```",
    "impact": -0.08,
    "agent": "秩序",
    "round": 1,
    "step": 1,
    "timestamp": "2025-07-14T07:10:11.089824",
    "reward": 0.632
  },
  {
    "action": "```json\n{\n  \"action\": \"凝聚初始防御屏障，吸收混沌元素中的不稳定因子\",\n  \"impact\": 0.85\n}\n```",
    "impact": -0.03,
    "agent": "存护",
    "round": 1,
    "step": 1,
    "timestamp": "2025-07-14T07:10:12.815823",
    "reward": 0.312
  },
  {
    "action": "观测并分析初始秩序框架的构建过程，推导混沌元素交融的数学规律",
    "impact": 0.75,
    "agent": "智识",
    "round": 1,
    "step": 1,
    "timestamp": "2025-07-14T07:10:14.333490",
    "reward": 0.6000000000000001
  },
  {
    "action": "```json\n{\n  \"action\": \"激发初始欢愉能量，催化混沌元素的交融与新奇形态诞生\",\n  \"impact\": 0.95\n}\n```",
    "impact": -0.15,
    "agent": "欢愉",
    "round": 1,
    "step": 1,
    "timestamp": "2025-07-14T07:10:16.138971",
    "reward": 0.6599999999999999
  },
  {
    "action": "```json\n{\n  \"action\": \"巡视混沌边界，锁定不稳定因子聚集区域以备后续清除\",\n  \"impact\": 0.82\n}\n```",
    "impact": 0.16,
    "agent": "巡猎",
    "round": 1,
    "step": 1,
    "timestamp": "2025-07-14T07:10:17.868306",
    "reward": 0.364
  },
  {
    "action": "引爆初始湮灭能量，直接瓦解混沌元素的原始交融结构",
    "impact": -0.98,
    "agent": "毁灭",
    "round": 1,
    "step": 1,
    "timestamp": "2025-07-14T07:10:19.117484",
    "reward": 0.692
  },
  {
    "action": "调和混沌元素间的冲突，平衡各初始力量的影响，防止任何单一趋势过度主导。",
    "impact": 0.2,
    "agent": "均衡",
    "round": 1,
    "step": 1,
    "timestamp": "2025-07-14T07:10:21.072798",
    "reward": 0.38
  },
  {
    "action": "散播虚无之种，在秩序框架的缝隙中孕育混沌裂隙",
    "impact": -0.93,
    "agent": "虚无",
    "round": 1,
    "step": 1,
    "timestamp": "2025-07-14T07:10:22.474388",
    "reward": 0.972
  },
  {
    "action": "引导混沌元素间的共鸣，增强初始和谐之光的渗透与融合效果",
    "impact": 0.83,
    "agent": "同谐",
    "round": 1,
    "step": 2,
    "timestamp": "2025-07-14T07:10:24.102505",
    "reward": 0.632
  },
  {
    "action": "记录混沌元素交融后的初始结构特征与能量分布图谱",
    "impact": 0.72,
    "agent": "记忆",
    "round": 1,
    "step": 2,
    "timestamp": "2025-07-14T07:10:25.631719",
    "reward": 0.588
  },
  {
    "action": "强化初始秩序框架的稳定性，修正混沌元素交融路径中的微小偏差",
    "impact": 0.88,
    "agent": "秩序",
    "round": 1,
    "step": 2,
    "timestamp": "2025-07-14T07:10:27.589730",
    "reward": 0.952
  },
  {
    "action": "凝聚初始防御屏障，吸收混沌元素中的不稳定因子",
    "impact": 0.85,
    "agent": "存护",
    "round": 1,
    "step": 2,
    "timestamp": "2025-07-14T07:10:28.909569",
    "reward": 0.64
  },
  {
    "action": "推演混沌元素的交融趋势，建立初始数学模型以预测后续演化路径",
    "impact": 0.8,
    "agent": "智识",
    "round": 1,
    "step": 2,
    "timestamp": "2025-07-14T07:10:30.325519",
    "reward": 0.6200000000000001
  },
  {
    "action": "激发初始欢愉能量，催化混沌元素的交融与新奇形态诞生",
    "impact": 0.95,
    "agent": "欢愉",
    "round": 1,
    "step": 2,
    "timestamp": "2025-07-14T07:10:31.671296",
    "reward": 0.98
  },
  {
    "action": "巡视混沌边界，锁定不稳定因子聚集区域以备后续清除",
    "impact": 0.16,
    "agent": "巡猎",
    "round": 1,
    "step": 2,
    "timestamp": "2025-07-14T07:10:32.861541",
    "reward": 0.364
  },
  {
    "action": "引爆初始湮灭火种，瓦解混沌根基并加速熵增进程",
    "impact": -0.98,
    "agent": "毁灭",
    "round": 1,
    "step": 2,
    "timestamp": "2025-07-14T07:10:34.250828",
    "reward": 0.692
  },
  {
    "action": "平衡各初始元素能量，确保和谐、秩序、防御与欢愉的动态稳定发展",
    "impact": 0.88,
    "agent": "均衡",
    "round": 1,
    "step": 2,
    "timestamp": "2025-07-14T07:10:35.680976",
    "reward": 0.652
  },
  {
    "action": "```json\n{\n  \"action\": \"腐蚀初始秩序框架，诱导混沌元素的无序离散与结构崩解\",\n  \"impact\": -0.92\n}\n```",
    "impact": -0.92,
    "agent": "虚无",
    "round": 1,
    "step": 2,
    "timestamp": "2025-07-14T07:10:39.388349",
    "reward": 0.668
  },
  {
    "action": "协调初始欢愉能量与防御屏障，平衡混沌元素的交融速率与稳定性",
    "impact": 0.88,
    "agent": "同谐",
    "round": 1,
    "step": 3,
    "timestamp": "2025-07-14T07:10:40.702679",
    "reward": 0.652
  },
  {
    "action": "深度铭刻混沌元素交融的初始形态与各代理作用轨迹，建立不可磨灭的记忆锚点",
    "impact": 0.92,
    "agent": "记忆",
    "round": 1,
    "step": 3,
    "timestamp": "2025-07-14T07:10:42.478547",
    "reward": 0.968
  },
  {
    "action": "修正混沌元素交融路径的偏差，确保秩序框架稳定成型",
    "impact": 0.88,
    "agent": "秩序",
    "round": 1,
    "step": 3,
    "timestamp": "2025-07-14T07:10:43.957973",
    "reward": 0.952
  },
  {
    "action": "凝聚初始防御屏障，吸收混沌元素中的不稳定因子",
    "impact": 0.85,
    "agent": "存护",
    "round": 1,
    "step": 3,
    "timestamp": "2025-07-14T07:10:45.388671",
    "reward": 0.64
  },
  {
    "action": "解析混沌元素交融的数学规律，推导初始秩序框架的稳定性方程",
    "impact": 0.8,
    "agent": "智识",
    "round": 1,
    "step": 3,
    "timestamp": "2025-07-14T07:10:47.354970",
    "reward": 0.6200000000000001
  },
  {
    "action": "激发初始欢愉能量，催化混沌元素的交融与新奇形态诞生",
    "impact": 0.95,
    "agent": "欢愉",
    "round": 1,
    "step": 3,
    "timestamp": "2025-07-14T07:10:48.808701",
    "reward": 0.98
  },
  {
    "action": "锁定混沌边界中的不稳定因子聚集区域，准备后续清除行动",
    "impact": 0.82,
    "agent": "巡猎",
    "round": 1,
    "step": 3,
    "timestamp": "2025-07-14T07:10:50.338842",
    "reward": 0.628
  },
  {
    "action": "释放初始崩坏波动，瓦解混沌元素中初生的过度代偿结构",
    "impact": -0.92,
    "agent": "毁灭",
    "round": 1,
    "step": 3,
    "timestamp": "2025-07-14T07:10:51.793080",
    "reward": 0.668
  },
  {
    "action": "调和混沌元素间的冲突能量，维持交融过程的动态平衡",
    "impact": 0.88,
    "agent": "均衡",
    "round": 1,
    "step": 3,
    "timestamp": "2025-07-14T07:10:53.527313",
    "reward": 0.652
  },
  {
    "action": "散播虚无之种，在秩序框架中埋下崩解的裂隙",
    "impact": -0.95,
    "agent": "虚无",
    "round": 1,
    "step": 3,
    "timestamp": "2025-07-14T07:10:54.844231",
    "reward": 0.98
  }
]